{
  "heroes": [
    {
      "name": "Thor",
      "description": "11111",
      "element": "wind",
      "id": "562b2b1d-320c-4d45-9b85-df32d6153c03"
    },
    {
      "name": "Arsenii",
      "description": "12123123",
      "element": "water",
      "id": "ddccfb94-eb3a-460b-8575-d2e1553a95c4"
    },
    {
      "name": "asdasd",
      "description": "asdasda",
      "element": "water",
      "id": "f1c2a0ee-7969-429b-88ae-9d2909ee61a7"
    },
    {
      "name": "Thor",
      "description": "zczxcv",
      "element": "fire",
      "id": "74bf887a-f3e5-4de8-ba19-a3a2e99779ea"
    },
    {
      "name": "Arsenii",
      "description": "asdasdas",
      "element": "wind",
      "id": "17a46b92-d3cf-4e9d-988e-1d7aec8083bc"
    }
  ],
  "filters": [
    {
      "id": "all",
      "name": "all",
      "filter": "all",
      "title": "Я владею элементом..."
    },
    {
      "id": "fire",
      "name": "fire",
      "filter": "fire",
      "title": "Огонь"
    },
    {
      "id": "water",
      "name": "water",
      "filter": "water",
      "title": "Вода"
    },
    {
      "id": "wind",
      "name": "wind",
      "filter": "wind",
      "title": "Ветер"
    },
    {
      "id": "earth",
      "name": "earth",
      "filter": "earth",
      "title": "Земля"
    }
  ]
}